searchypy/__init__.py
searchypy-0.0.1.dist-info/METADATA
searchypy-0.0.1.dist-info/WHEEL
searchypy-0.0.1.dist-info/licenses/LICENSE
searchypy-0.0.1.dist-info/RECORD
