Metadata-Version: 2.4
Name: searchypy
Version: 0.0.1
Summary: Placeholder package - SearchyPy is under active development
Project-URL: Homepage, https://github.com/mdasifbinkhaled/SortyPy
Project-URL: Repository, https://github.com/mdasifbinkhaled/SortyPy
Author-email: Md Asif Bin Khaled <mdasifbinkhaled@gmail.com>, Md Zakaria Kabir <zakariak5469@gmail.com>
License: Apache-2.0
License-File: LICENSE
Keywords: algorithms,placeholder,searching
Classifier: Development Status :: 1 - Planning
Classifier: Intended Audience :: Developers
Classifier: License :: OSI Approved :: Apache Software License
Classifier: Programming Language :: Python :: 3
Classifier: Programming Language :: Python :: 3.11
Classifier: Programming Language :: Python :: 3.12
Classifier: Programming Language :: Python :: 3.13
Requires-Python: >=3.11
